MetaPont/Contig_Coverage_Summary.py
MetaPont/Extract_By_Function.py
MetaPont/Extract_By_Taxa.py
MetaPont/Extract_Function_By_Taxa.py
MetaPont/Extract_Reads_By_Function.py
MetaPont/Function_By_Taxa.py
MetaPont/MetaPont_Combine.py
MetaPont/Report_Contig_Lineage.py
MetaPont/__init__.py
MetaPont/constants.py
metapont-0.0.10.dist-info/licenses/LICENSE
metapont-0.0.10.dist-info/METADATA
metapont-0.0.10.dist-info/WHEEL
metapont-0.0.10.dist-info/entry_points.txt
metapont-0.0.10.dist-info/top_level.txt
metapont-0.0.10.dist-info/RECORD
