Metadata-Version: 2.4
Name: MetaPont
Version: 0.0.10
Summary: MetaPont: A tool to bridge the gap between metagenomic tool output and its analysis.
Author-email: Nicholas Dimonaco <nicholas@dimonaco.co.uk>
License:                     GNU GENERAL PUBLIC LICENSE
Project-URL: Homepage, https://github.com/TheHuwsLab/MetaPont
Project-URL: Bug Tracker, https://github.com/TheHuwsLab/MetaPont/issues
Keywords: Metagenomics,Bioinformatics,Genomics
Classifier: Programming Language :: Python :: 3
Classifier: License :: OSI Approved :: GNU General Public License v3 (GPLv3)
Classifier: Operating System :: OS Independent
Requires-Python: >=3.10
License-File: LICENSE
Dynamic: license-file
